[
  {
    "title": "[상품] 비공개 문의 입니다. ",
    "userId": "K_1*********",
    "date": "2021.03.14 09:37:16",
    "option": "답변완료",
    "contents": "비공개 문의 입니다."
  },
  {
    "title": "[상품] 비공개 문의 입니다. ",
    "userId": "K_1*********",
    "date": "2021.03.14 09:37:16",
    "option": "답변완료",
    "contents": "비공개 문의 입니다."
  },
  {
    "title": "[상품] 비공개 문의 입니다. ",
    "userId": "K_1*********",
    "date": "2021.03.14 09:37:16",
    "option": "답변완료",
    "contents": "비공개 문의 입니다."
  },
  {
    "title": "[상품] 비공개 문의 입니다. ",
    "userId": "K_1*********",
    "date": "2021.03.14 09:37:16",
    "option": "답변완료",
    "contents": "비공개 문의 입니다."
  },
  {
    "title": "[상품] 비공개 문의 입니다. ",
    "userId": "K_1*********",
    "date": "2021.03.14 09:37:16",
    "option": "답변완료",
    "contents": "비공개 문의 입니다."
  },
  {
    "title": "[상품] 비공개 문의 입니다. ",
    "userId": "K_1*********",
    "date": "2021.03.14 09:37:16",
    "option": "답변완료",
    "contents": "비공개 문의 입니다."
  },
  {
    "title": "[상품] 비공개 문의 입니다. ",
    "userId": "K_1*********",
    "date": "2021.03.14 09:37:16",
    "option": "답변완료",
    "contents": "비공개 문의 입니다."
  },
  {
    "title": "[상품] 비공개 문의 입니다. ",
    "userId": "K_1*********",
    "date": "2021.03.14 09:37:16",
    "option": "답변완료",
    "contents": "비공개 문의 입니다."
  }
]
